{"cameraMode":{"drawMode":0,"name":"Shaded","section":"Shading Mode"},"sceneLighting":false,"audioPlay":false,"sceneViewState":{"showFog":true,"showMaterialUpdate":false,"showSkybox":false,"showFlares":true,"showImageEffects":true,"showParticleSystems":true},"in2DMode":false,"pivot":{"x":-0.027070164680480958,"y":3.565688371658325,"z":0.33762502670288088},"rotation":{"x":-0.0216987244784832,"y":0.9770349860191345,"z":0.17294006049633027,"w":0.12257120758295059},"size":14.074377059936524,"orthographic":false}